{
  "assessment_year": "2022-23",
  "pan": "FHOPR4213L",
  "employee_address": "158 Victoria Bakery Bldg. Mody Road Fort. Bengaluru,400001.India",
  "gross_salary": 2557983.0,
  "salary_section_17_1": 2557983.0,
  "prerequisites_section_17_2": 0.0,
  "profits_section_17_3": 0.0,
  "total_exemption_section_10": 180150.0,
  "standard_deduction_16_ia": 50000.0,
  "entertainment_allowance_16_ii": 0.0,
  "tax_on_employment_16_iii": 2400.0,
  "income_chargeable_salaries": 2325433.0,
  "gross_total_income": 2325433.0,
  "deduction_80C": 150000.0,
  "deduction_80CCC": 0.0,
  "deduction_80CCD1": 0.0,
  "deduction_80CCD1B": 0.0,
  "deduction_80CCD2": 0.0,
  "deduction_80D": 0.0,
  "deduction_80E": 0.0,
  "deduction_80G": 0.0,
  "deduction_80TTA": 0.0,
  "deduction_80C_total": 150000.0,
  "tax_on_total_income": 465132.0,
  "rebate_87A": "",
  "surcharge": 0.0,
  "health_education_cess": 18605.0,
  "relief_section_89": 0.0,
  "tax_payable": 483737.0
}